kairosdb/__init__.py
kairosdb/_api.py
kairosdb/_cnsts.py
kairosdb/_query.py
kairosdb/_utils/__init__.py
kairosdb/_utils/rest_client.py
kairosdb/errors/__init__.py
kairosdb_python-0.0.1.dist-info/LICENSE
kairosdb_python-0.0.1.dist-info/METADATA
kairosdb_python-0.0.1.dist-info/WHEEL
kairosdb_python-0.0.1.dist-info/top_level.txt
kairosdb_python-0.0.1.dist-info/RECORD
