Metadata-Version: 2.1
Name: kairosdb-python
Version: 0.0.1
Summary: Python Library for interacting with KairosDB
Home-page: https://github.com/iudeen/pykairosdb
Author: irfan
Author-email: irfanudeen08@gmail.com
License: MIT License
Platform: UNKNOWN
License-File: LICENSE
